wecom_notifier/__init__.py
wecom_notifier/constants.py
wecom_notifier/content_filter.py
wecom_notifier/content_moderator.py
wecom_notifier/exceptions.py
wecom_notifier/logger.py
wecom_notifier/models.py
wecom_notifier/moderation_strategies.py
wecom_notifier/notifier.py
wecom_notifier/rate_limiter.py
wecom_notifier/segmenter.py
wecom_notifier/sender.py
wecom_notifier/sensitive_logger.py
wecom_notifier/sensitive_word_loader.py
wecom_notifier/webhook_manager.py
wecom_notifier/webhook_pool.py
wecom_notifier/webhook_resource.py
wecom_notifier/core/__init__.py
wecom_notifier/core/constants.py
wecom_notifier/core/exceptions.py
wecom_notifier/core/logger.py
wecom_notifier/core/models.py
wecom_notifier/core/pool_base.py
wecom_notifier/core/protocols.py
wecom_notifier/core/rate_limiter.py
wecom_notifier/core/segmenter.py
wecom_notifier/core/moderation/__init__.py
wecom_notifier/core/moderation/filter.py
wecom_notifier/core/moderation/moderator.py
wecom_notifier/core/moderation/sensitive_logger.py
wecom_notifier/core/moderation/strategies.py
wecom_notifier/core/moderation/word_loader.py
wecom_notifier/platforms/__init__.py
wecom_notifier/platforms/feishu/__init__.py
wecom_notifier/platforms/feishu/adapter.py
wecom_notifier/platforms/feishu/constants.py
wecom_notifier/platforms/feishu/exceptions.py
wecom_notifier/platforms/feishu/notifier.py
wecom_notifier/platforms/feishu/rate_limiter.py
wecom_notifier/platforms/feishu/sender.py
wecom_notifier/platforms/wecom/__init__.py
wecom_notifier/platforms/wecom/adapter.py
wecom_notifier/platforms/wecom/constants.py
wecom_notifier/platforms/wecom/exceptions.py
wecom_notifier/platforms/wecom/manager.py
wecom_notifier/platforms/wecom/models.py
wecom_notifier/platforms/wecom/notifier.py
wecom_notifier/platforms/wecom/pool.py
wecom_notifier/platforms/wecom/resource.py
wecom_notifier/platforms/wecom/sender.py
wecom_notifier-0.3.1.dist-info/LICENSE
wecom_notifier-0.3.1.dist-info/METADATA
wecom_notifier-0.3.1.dist-info/WHEEL
wecom_notifier-0.3.1.dist-info/top_level.txt
wecom_notifier-0.3.1.dist-info/RECORD
