Metadata-Version: 2.1
Name: wecom-notifier
Version: 0.3.1
Summary: 多平台机器人通知组件，支持企业微信和飞书，提供频率控制、长文本分段、内容审核等功能
Author-email: ZLX <zj1123581321@gmail.com>
License: MIT License
Project-URL: Homepage, https://github.com/zj1123581321/wecom-notifier
Project-URL: Bug Reports, https://github.com/zj1123581321/wecom-notifier/issues
Project-URL: Source, https://github.com/zj1123581321/wecom-notifier
Project-URL: Documentation, https://github.com/zj1123581321/wecom-notifier#readme
Project-URL: Changelog, https://github.com/zj1123581321/wecom-notifier/blob/main/CHANGELOG.md
Keywords: wecom,wechat,enterprise-wechat,feishu,lark,robot,notification,webhook
Classifier: Development Status :: 4 - Beta
Classifier: Intended Audience :: Developers
Classifier: Topic :: Communications :: Chat
Classifier: Programming Language :: Python :: 3
Classifier: Programming Language :: Python :: 3.7
Classifier: Programming Language :: Python :: 3.8
Classifier: Programming Language :: Python :: 3.9
Classifier: Programming Language :: Python :: 3.10
Classifier: Programming Language :: Python :: 3.11
Classifier: Programming Language :: Python :: 3 :: Only
Classifier: Operating System :: OS Independent
Requires-Python: >=3.7
License-File: LICENSE
Requires-Dist: requests>=2.25.0
Requires-Dist: loguru>=0.7.0
Provides-Extra: dev
Requires-Dist: pytest>=6.0; extra == "dev"
Requires-Dist: pytest-cov>=2.0; extra == "dev"
Requires-Dist: build>=1.0.0; extra == "dev"
Requires-Dist: twine>=4.0.0; extra == "dev"
Provides-Extra: moderation
Requires-Dist: pypinyin>=0.44.0; extra == "moderation"
Requires-Dist: pyahocorasick>=2.0.0; extra == "moderation"
